Duke/DukeRestListener.py
Duke/__init__.py
Duke/agg_functions.py
Duke/class_tree.py
Duke/dataset.py
Duke/dataset_descriptor.py
Duke/embedding.py
Duke/evaluate.py
Duke/heuristic_evaluate.py
Duke/labels.py
Duke/test_rest.py
Duke/utils.py
Duke/ontologies/class-tree_dbpedia_2016-10.json
Duke/ontologies/class-tree_dbpedia_2016-10_pruned.json
d3m_duke-1.2.0.dist-info/LICENSE
d3m_duke-1.2.0.dist-info/METADATA
d3m_duke-1.2.0.dist-info/WHEEL
d3m_duke-1.2.0.dist-info/top_level.txt
d3m_duke-1.2.0.dist-info/RECORD
